LICENSE.txt
MANIFEST.in
README.rst
setup.cfg
setup.py
src/jupyter_latex_envs.egg-info/PKG-INFO
src/jupyter_latex_envs.egg-info/SOURCES.txt
src/jupyter_latex_envs.egg-info/dependency_links.txt
src/jupyter_latex_envs.egg-info/entry_points.txt
src/jupyter_latex_envs.egg-info/not-zip-safe
src/jupyter_latex_envs.egg-info/top_level.txt
src/latex_envs/__init__.py
src/latex_envs/latex_envs.py
src/latex_envs/static/README.md
src/latex_envs/static/bibInNb4.js
src/latex_envs/static/bibtex2.js
src/latex_envs/static/configuration_toolbar.png
src/latex_envs/static/envsLatex.js
src/latex_envs/static/example.png
src/latex_envs/static/example_user_envs.json
src/latex_envs/static/icon.png
src/latex_envs/static/initNb.js
src/latex_envs/static/latex_envs.css
src/latex_envs/static/latex_envs.js
src/latex_envs/static/latex_envs.yaml
src/latex_envs/static/main_toolbar.png
src/latex_envs/static/thmsInNb4.js
src/latex_envs/static/doc/IEEEtran.bst
src/latex_envs/static/doc/LaTeX_envs_menu.png
src/latex_envs/static/doc/README.md
src/latex_envs/static/doc/Toggles.png
src/latex_envs/static/doc/biblio_ipython.bib
src/latex_envs/static/doc/config_toolbar.png
src/latex_envs/static/doc/configuration_toolbar.png
src/latex_envs/static/doc/documentation.pdf
src/latex_envs/static/doc/documentation.tex
src/latex_envs/static/doc/example.png
src/latex_envs/static/doc/header.tex
src/latex_envs/static/doc/latex_env_doc.html
src/latex_envs/static/doc/latex_env_doc.ipynb
src/latex_envs/static/doc/latex_env_doc.tex
src/latex_envs/static/doc/main_toolbar.png
src/latex_envs/static/doc/latex_env_doc_files/latex_env_doc_23_2.png
src/latex_envs/static/doc/latex_env_doc_files/latex_env_doc_24_2.png
src/latex_envs/static/doc/latex_env_doc_files/latex_env_doc_26_2.png
src/latex_envs/static/doc/latex_env_doc_files/latex_env_doc_27_2.png
src/latex_envs/static/doc/latex_env_doc_files/latex_env_doc_41_0.png
src/latex_envs/static/doc/latex_env_doc_files/latex_env_doc_42_0.png
src/latex_envs/static/doc/latex_env_doc_files/latex_env_doc_43_0.png
src/latex_envs/static/doc/latex_env_doc_files/latex_env_doc_44_0.png
src/latex_envs/static/doc/latex_env_doc_files/latex_env_doc_45_0.png
src/latex_envs/static/doc/latex_env_doc_files/latex_env_doc_46_0.png
